faker_education/__init__.py
faker_education/constants.py
faker_education/schools.py
faker_education/tests/test_schools.py
faker_education-1.2.1.dist-info/LICENSE
faker_education-1.2.1.dist-info/WHEEL
faker_education-1.2.1.dist-info/METADATA
faker_education-1.2.1.dist-info/RECORD
