Metadata-Version: 2.1
Name: faker_education
Version: 1.2.1
Summary: Education Faker Community Provider
Author-email: Matt Henry <matthttam8411@gmail.com>
Classifier: License :: OSI Approved :: MIT License
Project-URL: Home, https://github.com/matthttam8411/faker_education.git
